simulinkwrapper/__init__.py
simulinkwrapper/noise.py
simulinkwrapper/simulations.py
simulinkwrapper-1.0.2.dist-info/LICENSE
simulinkwrapper-1.0.2.dist-info/METADATA
simulinkwrapper-1.0.2.dist-info/WHEEL
simulinkwrapper-1.0.2.dist-info/top_level.txt
simulinkwrapper-1.0.2.dist-info/RECORD
