Metadata-Version: 2.1
Name: simulinkwrapper
Version: 1.0.2
Summary: A Python wrapper for Simulink using the Matlab Python Engine.
Author-email: Miguel Santos Loureiro <miguel.santos.loureiro@gmail.com>
Maintainer-email: Miguel Santos Loureiro <miguel.santos.loureiro@gmail.com>
License:                                  Apache License
Keywords: Simulink,Wrapper,Simulations,Dynamical systems
Classifier: Programming Language :: Python :: 3
Classifier: License :: OSI Approved :: Apache Software License
Classifier: Natural Language :: English
Classifier: Operating System :: OS Independent
Classifier: Topic :: Software Development :: Libraries :: Python Modules
Classifier: Topic :: Scientific/Engineering
Classifier: Intended Audience :: Science/Research
Classifier: Intended Audience :: Developers
Classifier: Intended Audience :: Education
Requires-Python: >=3.10
License-File: LICENSE
Requires-Dist: numpy>=2.1.3
Requires-Dist: pandas>=2.2.3
Requires-Dist: matplotlib>=3.9.3
Requires-Dist: pyarrow>=18.1.0
Provides-Extra: dev
Requires-Dist: pytest>=8.3.4; extra == "dev"
